oga/__init__.py
oga/_helpers.py
oga/core.py
oga/parsing.py
oga/primitives.py
oga/main/__init__.py
oga/main/cli.py
oga-1.3.0.dist-info/LICENSE
oga-1.3.0.dist-info/METADATA
oga-1.3.0.dist-info/WHEEL
oga-1.3.0.dist-info/entry_points.txt
oga-1.3.0.dist-info/top_level.txt
oga-1.3.0.dist-info/RECORD
