Metadata-Version: 2.1
Name: oga
Version: 1.3.0
Summary: Library for interacting with OpenGameArt.org assets
Home-page: https://github.com/numberoverzero/oga
Author: Joe Cross
Author-email: joe.mcross@gmail.com
License: MIT
Platform: any
Requires-Dist: aiohttp (>=3.6)
Requires-Dist: beautifulsoup4 (>=4.9)
Requires-Dist: click (>=7.1)
